fit_psyche/__init__.py
fit_psyche/psychometric_curve.py
fit_psyche/models/__init__.py
fit_psyche/models/logit.py
fit_psyche/models/wh2001.py
tests/__init__.py
tests/unit/__init__.py
tests/unit/test_psychometric_curve.py
tests/unit/integration/__init__.py
tests/unit/integration/test_psychometric_curve.py
tests/unit/models/__init__.py
tests/unit/models/test_logit.py
tests/unit/models/test_wh2001.py
FitPsyche-0.1.0.dist-info/LICENSE
FitPsyche-0.1.0.dist-info/METADATA
FitPsyche-0.1.0.dist-info/WHEEL
FitPsyche-0.1.0.dist-info/top_level.txt
FitPsyche-0.1.0.dist-info/RECORD
