Metadata-Version: 2.1
Name: FitPsyche
Version: 0.1.0
Summary: Psychometric curve fitting package for Python and MATLAB.
Home-page: https://github.com/garethjns/PsychometricCurveFitting
Author: Gareth Jones
Author-email: garethgithub@gmail.com
Classifier: Programming Language :: Python :: 3
Classifier: Operating System :: OS Independent
Requires-Python: >=3.6
License-File: LICENSE
Requires-Dist: scipy
Requires-Dist: numpy
Requires-Dist: scikit-learn
Requires-Dist: matplotlib
